<?xml version="1.0" encoding="UTF-8"?>
<quiz>
<question id="27356">
        <parent>0</parent>
        <name>39.1.7.2 Probability Intervals Exercise 1</name>
        <questiontext>&lt;p class="HELM_exercise"&gt;Exercise&lt;/p&gt;

&lt;p&gt; Find the \({@displaydp(numa,2)@}\%\) probability interval for the standard Normal random variable \(Z\) centred at its mean.&lt;/p&gt;

&lt;p&gt;&lt;/p&gt;&lt;p&gt;(You &lt;b&gt;must&lt;/b&gt; give &lt;b&gt;all&lt;/b&gt; answers to &lt;b&gt;2 decimal places&lt;/b&gt;).&lt;/p&gt;&lt;p&gt;\(\text{P}(\) [[input:ans1]] \(&amp;lt; Z &amp;lt; \) [[input:ans2]]\() = {@displaydp(numa,2)@}\%\)&lt;/p&gt;&lt;p&gt;[[validation:ans1]][[validation:ans2]]&lt;/p&gt;&lt;p&gt;[[feedback:prt1]][[feedback:prt2]]&lt;/p&gt;</questiontext>
        <questiontextformat>1</questiontextformat>
        <generalfeedback>&lt;h4 class="HELM_solution"&gt;Solution&lt;/h4&gt;

&lt;p&gt;As the interval is centred on about the mean of the standard Normal random variable \(Z \sim N(0,1)\), then \(z_1 = -z_2\) and the probability of this interval can be expressed as follows using the symmetry of the distribution:&lt;/p&gt;&lt;p&gt;\[ \text{P}(z_1 &amp;lt; Z &amp;lt; z_2) = 2 \times \text{P}(0 &amp;lt; Z &amp;lt; z_2)\]&lt;/p&gt;&lt;p&gt;For this probability to be \({@displaydp(numa,2)@}\%\), we need to find \(z_2\) such that \[\text{P}(0 &amp;lt; Z &amp;lt; z_2) = \dfrac{{@displaydp(numa/100,4)@}}{2} = {@displaydp(ptab,4)@}.\]&lt;/p&gt;&lt;p&gt;Reading from the standard Normal table we see that \(z_2 = {@displaydp(ta2,2)@}\), hence:&lt;/p&gt;&lt;p&gt;\[&amp;nbsp;\text{P}({@displaydp(ta1,2)@} &amp;lt; Z &amp;lt; {@displaydp(ta2,2)@}) = {@displaydp(numa,2)@}\%.\]&lt;/p&gt;</generalfeedback>
        <generalfeedbackformat>1</generalfeedbackformat>
        <defaultmark>1.0000000</defaultmark>
        <penalty>0.0000000</penalty>
        <qtype>stack</qtype>
        <length>1</length>
        <stamp>stack2.maths.ed.ac.uk+200727100547+mg9C8o</stamp>
        <version>stack-back1.maths.ed.ac.uk+211014160638+DFm4Lf</version>
        <hidden>0</hidden>
        <timecreated>1595844347</timecreated>
        <timemodified>1634227598</timemodified>
        <createdby>642</createdby>
        <modifiedby>820</modifiedby>
        <idnumber>$@NULL@$</idnumber>
        <plugin_qtype_stack_question>
          <stackoptions id="18475">
            <stackversion>2021072200</stackversion>
            <questionvariables>z: decimalplaces(float(rand_with_step(2.40, 2.59, 0.01)),2);
ptab: decimalplaces(float(cdf_normal(z,0,1)-0.5),4);
numa: decimalplaces(float(100*2*ptab),2);
zEXACT: decimalplaces(float(quantile_normal(0.5+numa/200,0,1)),2);

ta1: -z;
ta2: z;



/*
tablea:rand([4918, 4920, 4922, 4925, 4927, 4929, 4931, 4932, 4934, 4936, 4938, 4940, 4941, 4943, 4946, 4947, 4948, 4949, 4951, 4952])
enta:decimalplaces(float(tablea/10000),4)
proba:decimalplaces(float(enta*2),4)
numa:decimalplaces(float(proba*100),2)
ta1:decimalplaces(quantile_normal(float(enta+0.5),0,1),2)
ta2:-ta1
ta3:ta1
commenta:decimalplaces(float(100-numa),2)
*/</questionvariables>
            <specificfeedback/>
            <specificfeedbackformat>1</specificfeedbackformat>
            <questionnote>z: \({@displaydp(z,2)@}\), ptab: \({@displaydp(ptab,4)@}\), numa: \({@displaydp(numa,2)@}\%\), zEXACT: \({@displaydp(zEXACT,2)@}\)</questionnote>
            <questionsimplify>1</questionsimplify>
            <assumepositive>0</assumepositive>
            <assumereal>0</assumereal>
            <prtcorrect>&lt;span style="font-size: 1.5em; color:green;"&gt;&lt;i class="fa fa-check"&gt;&lt;/i&gt;&lt;/span&gt; Correct answer, well done.</prtcorrect>
            <prtcorrectformat>1</prtcorrectformat>
            <prtpartiallycorrect>&lt;span style="font-size: 1.5em; color:orange;"&gt;&lt;i class="fa fa-adjust"&gt;&lt;/i&gt;&lt;/span&gt; Your answer is partially correct.</prtpartiallycorrect>
            <prtpartiallycorrectformat>1</prtpartiallycorrectformat>
            <prtincorrect>&lt;span style="font-size: 1.5em; color:red;"&gt;&lt;i class="fa fa-times"&gt;&lt;/i&gt;&lt;/span&gt; Incorrect answer.</prtincorrect>
            <prtincorrectformat>1</prtincorrectformat>
            <multiplicationsign>dot</multiplicationsign>
            <sqrtsign>1</sqrtsign>
            <complexno>i</complexno>
            <inversetrig>cos-1</inversetrig>
            <logicsymbol>lang</logicsymbol>
            <matrixparens>[</matrixparens>
            <variantsselectionseed/>
          </stackoptions>
          <stackinputs>
            <stackinput id="43655">
              <name>ans1</name>
              <type>numerical</type>
              <tans>dispdp(ta1,2)</tans>
              <boxsize>8</boxsize>
              <strictsyntax>1</strictsyntax>
              <insertstars>0</insertstars>
              <syntaxhint>to 2 d.p.</syntaxhint>
              <syntaxattribute>1</syntaxattribute>
              <forbidwords/>
              <allowwords/>
              <forbidfloat>0</forbidfloat>
              <requirelowestterms>0</requirelowestterms>
              <checkanswertype>1</checkanswertype>
              <mustverify>1</mustverify>
              <showvalidation>3</showvalidation>
              <options>maxdp:2, mindp:2</options>
            </stackinput>
            <stackinput id="43656">
              <name>ans2</name>
              <type>numerical</type>
              <tans>dispdp(ta2,2)</tans>
              <boxsize>8</boxsize>
              <strictsyntax>1</strictsyntax>
              <insertstars>0</insertstars>
              <syntaxhint>to 2 d.p.</syntaxhint>
              <syntaxattribute>1</syntaxattribute>
              <forbidwords/>
              <allowwords/>
              <forbidfloat>0</forbidfloat>
              <requirelowestterms>0</requirelowestterms>
              <checkanswertype>1</checkanswertype>
              <mustverify>1</mustverify>
              <showvalidation>3</showvalidation>
              <options>maxdp:2, mindp:2</options>
            </stackinput>
          </stackinputs>
          <stackprts>
            <stackprt id="37915">
              <name>prt1</name>
              <value>1.0000000</value>
              <autosimplify>1</autosimplify>
              <feedbackstyle>1</feedbackstyle>
              <feedbackvariables/>
              <stackprtnodes>
                <stackprtnode id="56505">
                  <nodename>0</nodename>
                  <answertest>NumDecPlaces</answertest>
                  <sans>ans1</sans>
                  <tans>ta1</tans>
                  <testoptions>2</testoptions>
                  <quiet>0</quiet>
                  <truescoremode>=</truescoremode>
                  <truescore>1.0000000</truescore>
                  <truepenalty>$@NULL@$</truepenalty>
                  <truenextnode>-1</truenextnode>
                  <trueanswernote>prt1-1-T</trueanswernote>
                  <truefeedback/>
                  <truefeedbackformat>1</truefeedbackformat>
                  <falsescoremode>=</falsescoremode>
                  <falsescore>0.0000000</falsescore>
                  <falsepenalty>$@NULL@$</falsepenalty>
                  <falsenextnode>1</falsenextnode>
                  <falseanswernote>prt1-1-F</falseanswernote>
                  <falsefeedback/>
                  <falsefeedbackformat>1</falsefeedbackformat>
                </stackprtnode>
                <stackprtnode id="118419">
                  <nodename>1</nodename>
                  <answertest>NumDecPlaces</answertest>
                  <sans>ans1</sans>
                  <tans>-zEXACT</tans>
                  <testoptions>2</testoptions>
                  <quiet>1</quiet>
                  <truescoremode>+</truescoremode>
                  <truescore>1.0000000</truescore>
                  <truepenalty>$@NULL@$</truepenalty>
                  <truenextnode>-1</truenextnode>
                  <trueanswernote>prt1-2-T</trueanswernote>
                  <truefeedback/>
                  <truefeedbackformat>1</truefeedbackformat>
                  <falsescoremode>-</falsescoremode>
                  <falsescore>0.0000000</falsescore>
                  <falsepenalty>$@NULL@$</falsepenalty>
                  <falsenextnode>-1</falsenextnode>
                  <falseanswernote>prt1-2-F</falseanswernote>
                  <falsefeedback/>
                  <falsefeedbackformat>1</falsefeedbackformat>
                </stackprtnode>
              </stackprtnodes>
            </stackprt>
            <stackprt id="37916">
              <name>prt2</name>
              <value>1.0000000</value>
              <autosimplify>1</autosimplify>
              <feedbackstyle>1</feedbackstyle>
              <feedbackvariables/>
              <stackprtnodes>
                <stackprtnode id="56506">
                  <nodename>0</nodename>
                  <answertest>NumDecPlaces</answertest>
                  <sans>ans2</sans>
                  <tans>ta2</tans>
                  <testoptions>2</testoptions>
                  <quiet>0</quiet>
                  <truescoremode>=</truescoremode>
                  <truescore>1.0000000</truescore>
                  <truepenalty>$@NULL@$</truepenalty>
                  <truenextnode>-1</truenextnode>
                  <trueanswernote>prt2-1-T</trueanswernote>
                  <truefeedback/>
                  <truefeedbackformat>1</truefeedbackformat>
                  <falsescoremode>=</falsescoremode>
                  <falsescore>0.0000000</falsescore>
                  <falsepenalty>$@NULL@$</falsepenalty>
                  <falsenextnode>1</falsenextnode>
                  <falseanswernote>prt2-1-F</falseanswernote>
                  <falsefeedback/>
                  <falsefeedbackformat>1</falsefeedbackformat>
                </stackprtnode>
                <stackprtnode id="118420">
                  <nodename>1</nodename>
                  <answertest>NumDecPlaces</answertest>
                  <sans>ans2</sans>
                  <tans>zEXACT</tans>
                  <testoptions>2</testoptions>
                  <quiet>0</quiet>
                  <truescoremode>+</truescoremode>
                  <truescore>1.0000000</truescore>
                  <truepenalty>$@NULL@$</truepenalty>
                  <truenextnode>-1</truenextnode>
                  <trueanswernote>prt2-2-T</trueanswernote>
                  <truefeedback/>
                  <truefeedbackformat>1</truefeedbackformat>
                  <falsescoremode>-</falsescoremode>
                  <falsescore>0.0000000</falsescore>
                  <falsepenalty>$@NULL@$</falsepenalty>
                  <falsenextnode>-1</falsenextnode>
                  <falseanswernote>prt2-2-F</falseanswernote>
                  <falsefeedback/>
                  <falsefeedbackformat>1</falsefeedbackformat>
                </stackprtnode>
              </stackprtnodes>
            </stackprt>
          </stackprts>
          <stackqtests>
            <stackqtest id="42616">
              <testcase>1</testcase>
              <timemodified>1597315144</timemodified>
              <stackqtestinputs>
                <stackqtestinput id="92990">
                  <inputname>ans1</inputname>
                  <value>dispdp(ta1,2)</value>
                </stackqtestinput>
                <stackqtestinput id="92991">
                  <inputname>ans2</inputname>
                  <value>dispdp(ta2,2)</value>
                </stackqtestinput>
              </stackqtestinputs>
              <stackqtestexpecteds>
                <stackqtestexpected id="80694">
                  <prtname>prt1</prtname>
                  <expectedscore>1.0000000</expectedscore>
                  <expectedpenalty>0.0000000</expectedpenalty>
                  <expectedanswernote>prt1-1-T</expectedanswernote>
                </stackqtestexpected>
                <stackqtestexpected id="80695">
                  <prtname>prt2</prtname>
                  <expectedscore>1.0000000</expectedscore>
                  <expectedpenalty>0.0000000</expectedpenalty>
                  <expectedanswernote>prt2-1-T</expectedanswernote>
                </stackqtestexpected>
              </stackqtestexpecteds>
            </stackqtest>
            <stackqtest id="42617">
              <testcase>2</testcase>
              <timemodified>1634227580</timemodified>
              <stackqtestinputs>
                <stackqtestinput id="196273">
                  <inputname>ans1</inputname>
                  <value>dispdp(ta2,2)</value>
                </stackqtestinput>
                <stackqtestinput id="196274">
                  <inputname>ans2</inputname>
                  <value>dispdp(ta1,2)</value>
                </stackqtestinput>
              </stackqtestinputs>
              <stackqtestexpecteds>
                <stackqtestexpected id="168687">
                  <prtname>prt1</prtname>
                  <expectedscore>0.0000000</expectedscore>
                  <expectedpenalty>0.0000000</expectedpenalty>
                  <expectedanswernote>prt1-2-F</expectedanswernote>
                </stackqtestexpected>
                <stackqtestexpected id="168688">
                  <prtname>prt2</prtname>
                  <expectedscore>0.0000000</expectedscore>
                  <expectedpenalty>0.0000000</expectedpenalty>
                  <expectedanswernote>prt2-2-F</expectedanswernote>
                </stackqtestexpected>
              </stackqtestexpecteds>
            </stackqtest>
          </stackqtests>
          <stackdeployedseeds>
            <stackdeployedseed id="179934">
              <seed>1163319956</seed>
            </stackdeployedseed>
            <stackdeployedseed id="179936">
              <seed>304331310</seed>
            </stackdeployedseed>
            <stackdeployedseed id="179937">
              <seed>913962843</seed>
            </stackdeployedseed>
            <stackdeployedseed id="179938">
              <seed>299014047</seed>
            </stackdeployedseed>
            <stackdeployedseed id="179939">
              <seed>379529735</seed>
            </stackdeployedseed>
            <stackdeployedseed id="179940">
              <seed>1543667084</seed>
            </stackdeployedseed>
            <stackdeployedseed id="179941">
              <seed>303568879</seed>
            </stackdeployedseed>
            <stackdeployedseed id="179942">
              <seed>436988941</seed>
            </stackdeployedseed>
            <stackdeployedseed id="179943">
              <seed>48846871</seed>
            </stackdeployedseed>
          </stackdeployedseeds>
        </plugin_qtype_stack_question>
        <question_hints>
        </question_hints>
        <tags>
        </tags>
      </question>
      

</quiz>